barycorrpy/PINT_erfautils.py
barycorrpy/PhysicalConstants.py
barycorrpy/SolarSystemBC.py
barycorrpy/__init__.py
barycorrpy/barycorrpy.py
barycorrpy/sample_script.py
barycorrpy/utc_tdb.py
barycorrpy/utils.py
barycorrpy/data/hip2.dat
barycorrpy/tests/__init__.py
barycorrpy/tests/test_barycorrpy.py
barycorrpy-0.4.4.dist-info/LICENSE.txt
barycorrpy-0.4.4.dist-info/METADATA
barycorrpy-0.4.4.dist-info/WHEEL
barycorrpy-0.4.4.dist-info/top_level.txt
barycorrpy-0.4.4.dist-info/RECORD
