Metadata-Version: 2.1
Name: barycorrpy
Version: 0.4.4
Summary: Barycentric Velocity correction at 1 cm/s level
Home-page: https://github.com/shbhuk/barycorrpy
Author: Shubham Kanodia
Author-email: shbhuk@gmail.com
License: GPLv3
Keywords: Barycentric Correction Astronomy Spectroscopy Radial Velocity
Platform: UNKNOWN
Classifier: Topic :: Scientific/Engineering :: Astronomy
Requires-Dist: astropy (>=4.0.4)
Requires-Dist: jplephem
Requires-Dist: numpy (>=1.17.2)
Requires-Dist: scipy
Requires-Dist: astroquery (>=0.3.10)
Requires-Dist: pyerfa (>=1.7.3)
